{"$schema":"http:\/\/wso2.org\/json-schema\/wso2-data-mapper-v5.0.0\/schema#","outputType":"JSON","id":"http:\/\/wso2jsonschema.org","title":"root","type":"object","properties":{"req":{"id":"http:\/\/wso2jsonschema.org\/req","type":"array","items":[{"id":"http:\/\/wso2jsonschema.org\/req\/0","type":"object","properties":{"enty":{"id":"http:\/\/wso2jsonschema.org\/req\/0\/enty","type":"array","items":[{"id":"http:\/\/wso2jsonschema.org\/req\/0\/enty\/0","type":"object","properties":{"entypes":{"id":"","type":"array","items":[{"id":"\/0","type":"object","properties":{"name":{"id":"null\/0","type":"string"},"id":{"id":"null\/0","type":"number"}}}]},"name":{"id":"http:\/\/wso2jsonschema.org\/req\/0\/enty\/0\/name","type":"string"},"id":{"id":"http:\/\/wso2jsonschema.org\/req\/0\/enty\/0\/id","type":"number"},"entity_type_id":{"id":"http:\/\/wso2jsonschema.org\/req\/0\/enty\/0\/entity_type_id","type":"number"}}}]},"experiment_name":{"id":"http:\/\/wso2jsonschema.org\/req\/0\/experiment_name","type":"string"},"id":{"id":"http:\/\/wso2jsonschema.org\/req\/0\/id","type":"string"},"ticket_number":{"id":"http:\/\/wso2jsonschema.org\/req\/0\/ticket_number","type":"string"}}}]}}}